{
  "$schema": "http://json-schema.org/draft-07/schema#",
  "$id": "https://gokapi.dev/schemas/filters/okf_transtable.schema.json",
  "$version": "1.0.0",
  "title": "TransTable Filter Filter",
  "description": "Configuration for the Okapi TransTable Filter Filter",
  "type": "object",
  "x-filter": {
    "id": "okf_transtable",
    "class": "net.sf.okapi.filters.transtable.TransTableFilter",
    "extensions": [],
    "mimeTypes": [
      "text/x-transtable"
    ],
    "configurations": [
      {
        "configId": "okf_transtable",
        "name": "Translation Table Default",
        "description": "Default TransTable configuration.",
        "mimeType": "text/x-transtable",
        "isDefault": true,
        "filterClass": "net.sf.okapi.filters.transtable.TransTableFilter"
      }
    ],
    "serializationFormat": "yaml"
  },
  "properties": {},
  "additionalProperties": false
}