{
  "$id": "paragraph-aligner",
  "title": "Paragraph Alignment",
  "type": "object",
  "x-step": {
    "class": "net.sf.okapi.steps.paraaligner.ParagraphAlignerStep",
    "parameterMappings": [
      "FILTER_CONFIGURATION_MAPPER",
      "SECOND_INPUT_RAWDOC",
      "SOURCE_LOCALE",
      "TARGET_LOCALE"
    ],
    "eventHandlers": [
      "handleDocumentPart",
      "handleEndBatch",
      "handleEndDocument",
      "handleEndGroup",
      "handleEndSubDocument",
      "handleStartBatch",
      "handleStartDocument",
      "handleStartGroup",
      "handleStartSubDocument",
      "handleTextUnit"
    ],
    "interfaces": [],
    "inputType": "filter-events",
    "outputType": "filter-events"
  },
  "x-component": {
    "id": "paragraph-aligner",
    "type": "step",
    "displayName": "Paragraph Alignment",
    "description": "Align paragraphs (text units) between a source and a target document. Only TextUnit events are passed along - all other events are lost",
    "category": "pipeline",
    "inputs": [
      "block",
      "data"
    ],
    "tags": [
      "text-processing"
    ],
    "requires": [
      "target-language",
      "source-language"
    ]
  },
  "properties": {
    "outputOneToOneMatchesOnly": {
      "type": "boolean",
      "default": true,
      "title": "Output 1-1 Matches Only?",
      "description": "Ouput only 1-1 aligned paragraphs?",
      "x-widget": "checkbox",
      "x-vertical": true
    },
    "useSkeletonAlignment": {
      "type": "boolean",
      "default": false,
      "title": "Use Skeleton Alignment? (Experimental)",
      "description": "Use Skeleton alignment? (Experimental)",
      "x-widget": "checkbox",
      "x-vertical": true
    }
  }
}