{
  "$schema": "http://json-schema.org/draft-07/schema#",
  "title": "Json Filter Filter",
  "description": "Configuration for the Okapi Json Filter Filter",
  "type": "object",
  "x-filter": {
    "id": "okf_json",
    "class": "net.sf.okapi.filters.json.JSONFilter",
    "extensions": [
      ".json"
    ],
    "mimeTypes": [
      "application/json"
    ],
    "configurations": [
      {
        "configId": "okf_json",
        "name": "JSON (JavaScript Object Notation)",
        "description": "Configuration for JSON files",
        "mimeType": "application/json",
        "extensions": ".json;",
        "isDefault": true,
        "filterClass": "net.sf.okapi.filters.json.JSONFilter"
      }
    ],
    "serializationFormat": "stringParameters"
  },
  "properties": {
    "inlineCodes": {
      "$ref": "#/$defs/inlineCodes"
    },
    "extraction": {
      "type": "object",
      "description": "Control what content is extracted for translation",
      "properties": {
        "extractAll": {
          "type": "boolean",
          "default": true,
          "x-flattenPath": "extractAllPairs",
          "description": "Extract all key-value pairs"
        },
        "pathRules": {
          "type": "string",
          "default": "",
          "x-flattenPath": "extractionRules",
          "description": "Regex for JSON paths to extract"
        },
        "includeIsolatedStrings": {
          "type": "boolean",
          "default": false,
          "x-flattenPath": "extractIsolatedStrings",
          "description": "Extract array string values without keys"
        },
        "excludeKeys": {
          "type": "string",
          "default": "",
          "x-flattenPath": "exceptions",
          "description": "Comma-separated keys to exclude from extraction"
        },
        "subfilterRules": {
          "type": "string",
          "default": "",
          "x-flattenPath": "subfilterRules",
          "description": "Sub-filter rules for embedded content"
        }
      }
    },
    "keys": {
      "type": "object",
      "description": "Configure how JSON keys map to text unit identification",
      "properties": {
        "useAsName": {
          "type": "boolean",
          "default": true,
          "x-flattenPath": "useKeyAsName",
          "description": "Use JSON key as text unit name"
        },
        "useFullPath": {
          "type": "boolean",
          "default": false,
          "x-flattenPath": "useFullKeyPath",
          "description": "Use full path (/key1/key2) as name"
        },
        "leadingSlash": {
          "type": "boolean",
          "default": true,
          "x-flattenPath": "useLeadingSlashOnKeyPath",
          "description": "Include leading slash in paths"
        },
        "idRules": {
          "type": "string",
          "default": "",
          "x-flattenPath": "idRules",
          "description": "Regex for keys used as text unit IDs"
        }
      }
    },
    "metadata": {
      "type": "object",
      "description": "Configure metadata extraction rules",
      "properties": {
        "noteRules": {
          "type": "string",
          "default": "",
          "x-flattenPath": "noteRules",
          "description": "Regex for translator note keys"
        },
        "metaRules": {
          "type": "string",
          "default": "",
          "x-flattenPath": "genericMetaRules",
          "description": "Regex for generic metadata keys"
        }
      }
    },
    "output": {
      "type": "object",
      "description": "Output formatting options",
      "properties": {
        "escapeSlashes": {
          "type": "boolean",
          "default": true,
          "x-flattenPath": "escapeForwardSlashes",
          "description": "Escape forward slashes in output"
        }
      }
    }
  },
  "additionalProperties": false,
  "$defs": {
    "inlineCodes": {
      "type": "object",
      "description": "Inline code detection and handling",
      "properties": {
        "enabled": {
          "type": "boolean",
          "default": false,
          "description": "Enable pattern-based detection of inline codes",
          "x-flattenPath": "useCodeFinder"
        },
        "rules": {
          "$ref": "#/$defs/codeFinderRules",
          "x-flattenPath": "codeFinderRules"
        },
        "mergeAdjacent": {
          "type": "boolean",
          "description": "Merge consecutive inline codes into a single placeholder",
          "x-flattenPath": "mergeAdjacentCodes"
        },
        "moveBoundaryCodes": {
          "type": "boolean",
          "description": "Move codes at segment boundaries to the skeleton",
          "x-flattenPath": "moveLeadingAndTrailingCodesToSkeleton"
        },
        "simplifierRules": {
          "$ref": "#/$defs/simplifierRules",
          "x-flattenPath": "simplifierRules"
        }
      }
    },
    "codeFinderRules": {
      "type": "object",
      "description": "Regex patterns for inline code detection",
      "properties": {
        "rules": {
          "type": "array",
          "description": "List of regex patterns to detect inline codes",
          "items": {
            "type": "object",
            "properties": {
              "pattern": {
                "type": "string",
                "description": "Regex pattern for inline code detection"
              }
            },
            "required": [
              "pattern"
            ]
          }
        },
        "sample": {
          "type": "string",
          "description": "Sample text to test patterns against"
        },
        "useAllRulesWhenTesting": {
          "type": "boolean",
          "default": true,
          "description": "Test all rules together or individually"
        }
      },
      "x-okapiFormat": "inlineCodeFinder"
    },
    "simplifierRules": {
      "type": "string",
      "description": "Rules for simplifying inline code representation",
      "x-widget": "simplifierRulesEditor"
    }
  }
}